aparser_async_api/__init__.py
aparser_async_api/main.py
aparser_async_api-1.0.1.dist-info/LICENSE
aparser_async_api-1.0.1.dist-info/METADATA
aparser_async_api-1.0.1.dist-info/WHEEL
aparser_async_api-1.0.1.dist-info/top_level.txt
aparser_async_api-1.0.1.dist-info/RECORD
