Metadata-Version: 2.1
Name: aparser-async-api
Version: 1.0.1
Summary: Asyncio is an alternative module for working with A-parser.
Home-page: https://github.com/DvaMishkiLapa/aparser-async-api
Author: Utkin Artem
Author-email: thesame.personal@gmail.com
License: UNKNOWN
Platform: UNKNOWN
Classifier: Programming Language :: Python :: 3
Classifier: License :: OSI Approved :: Apache Software License
Classifier: Operating System :: OS Independent
Requires-Python: >=3.8
License-File: LICENSE
Requires-Dist: aiohttp (>=3.8)
